setup.cfg
setup.py
lava/__init__.py
lava/android/__init__.py
lava/android/extension.py
lava/android/models.py
lava/android/tests.py
lava/android/views.py
lava/android/management/__init__.py
lava/android/management/commands/__init__.py
lava/android/management/commands/dump_android_data.py
lava/android/management/commands/find_android_builds.py
lava/android/migrations/0001_initial.py
lava/android/migrations/__init__.py
lava_android.egg-info/PKG-INFO
lava_android.egg-info/SOURCES.txt
lava_android.egg-info/dependency_links.txt
lava_android.egg-info/entry_points.txt
lava_android.egg-info/namespace_packages.txt
lava_android.egg-info/requires.txt
lava_android.egg-info/top_level.txt
lava_android.egg-info/zip-safe