Metadata-Version: 1.0
Name: lava-android
Version: 0.1.dev13
Summary: Magic sauce for Android and LAVA
Home-page: UNKNOWN
Author: Zygmunt Krynicki
Author-email: zygmunt.krynicki@linaro.org
License: AGPL
Platform: UNKNOWN
Classifier: Development Status :: 3 - Alpha
Classifier: Intended Audience :: Developers
Classifier: License :: OSI Approved :: GNU Affero General Public License v3
Classifier: Operating System :: OS Independent
Classifier: Programming Language :: Python :: 2.7
Classifier: Topic :: Software Development :: Testing
